odoo/addons/fastapi/README.rst
odoo/addons/fastapi/__init__.py
odoo/addons/fastapi/__manifest__.py
odoo/addons/fastapi/context.py
odoo/addons/fastapi/dependencies.py
odoo/addons/fastapi/depends.py
odoo/addons/fastapi/error_handlers.py
odoo/addons/fastapi/fastapi_dispatcher.py
odoo/addons/fastapi/middleware.py
odoo/addons/fastapi/schemas.py
odoo/addons/fastapi/demo/fastapi_endpoint_demo.xml
odoo/addons/fastapi/i18n/fastapi.pot
odoo/addons/fastapi/i18n/it.po
odoo/addons/fastapi/models/__init__.py
odoo/addons/fastapi/models/fastapi_endpoint.py
odoo/addons/fastapi/models/fastapi_endpoint_demo.py
odoo/addons/fastapi/models/ir_rule.py
odoo/addons/fastapi/models/res_lang.py
odoo/addons/fastapi/pools/__init__.py
odoo/addons/fastapi/pools/event_loop.py
odoo/addons/fastapi/pools/fastapi_app.py
odoo/addons/fastapi/readme/CONTRIBUTORS.md
odoo/addons/fastapi/readme/DESCRIPTION.md
odoo/addons/fastapi/readme/HISTORY.md
odoo/addons/fastapi/readme/ROADMAP.md
odoo/addons/fastapi/readme/USAGE.md
odoo/addons/fastapi/readme/newsfragments/.gitignore
odoo/addons/fastapi/routers/__init__.py
odoo/addons/fastapi/routers/demo_router.py
odoo/addons/fastapi/security/fastapi_endpoint.xml
odoo/addons/fastapi/security/ir_rule+acl.xml
odoo/addons/fastapi/security/res_groups.xml
odoo/addons/fastapi/static/description/endpoint_create.png
odoo/addons/fastapi/static/description/icon.png
odoo/addons/fastapi/static/description/index.html
odoo/addons/fastapi/tests/__init__.py
odoo/addons/fastapi/tests/common.py
odoo/addons/fastapi/tests/test_fastapi.py
odoo/addons/fastapi/tests/test_fastapi_demo.py
odoo/addons/fastapi/views/fastapi_endpoint.xml
odoo/addons/fastapi/views/fastapi_endpoint_demo.xml
odoo/addons/fastapi/views/fastapi_menu.xml
odoo_addon_fastapi-18.0.1.3.2.dist-info/METADATA
odoo_addon_fastapi-18.0.1.3.2.dist-info/WHEEL
odoo_addon_fastapi-18.0.1.3.2.dist-info/top_level.txt
odoo_addon_fastapi-18.0.1.3.2.dist-info/RECORD
