Metadata-Version: 2.1
Name: odoo-addon-fastapi
Version: 18.0.1.3.2
Requires-Python: >=3.10
Requires-Dist: a2wsgi>=1.10.6
Requires-Dist: fastapi>=0.110.0
Requires-Dist: odoo-addon-endpoint_route_handler==18.0.*
Requires-Dist: odoo==18.0.*
Requires-Dist: parse-accept-language
Requires-Dist: python-multipart
Requires-Dist: ujson
Summary: Odoo FastAPI endpoint
Home-page: https://github.com/OCA/rest-framework
License: LGPL-3
Author: ACSONE SA/NV,Odoo Community Association (OCA)
Author-email: support@odoo-community.org
Classifier: Programming Language :: Python
Classifier: Framework :: Odoo
Classifier: Framework :: Odoo :: 18.0
Classifier: License :: OSI Approved :: GNU Lesser General Public License v3 (LGPLv3)
Classifier: Development Status :: 4 - Beta
